{"ProjectBreakpoints":"{\"CodeBreakpoints\":{},\"Value\":{}}","OpenedDocuments":"[]","ProjectActivitiesViewState":"{\"Main.xaml\":[{\"ActivityIdRef\":\"ShouldStop_2\",\"IsAdvancedOptionsExpanded\":false,\"Widgets\":{}},{\"ActivityIdRef\":\"If_11\",\"IsAdvancedOptionsExpanded\":false,\"Widgets\":{\"Then\":{\"ShowExpanded\":true},\"Else\":{\"ShowExpanded\":false}}},{\"ActivityIdRef\":\"If_1\",\"IsAdvancedOptionsExpanded\":false,\"Widgets\":{\"Then\":{\"ShowExpanded\":true},\"Else\":{\"ShowExpanded\":false}}},{\"ActivityIdRef\":\"If_10\",\"IsAdvancedOptionsExpanded\":false,\"Widgets\":{\"Then\":{\"ShowExpanded\":true},\"Else\":{\"ShowExpanded\":false}}},{\"ActivityIdRef\":\"If_12\",\"IsAdvancedOptionsExpanded\":false,\"Widgets\":{\"Then\":{\"ShowExpanded\":true},\"Else\":{\"ShowExpanded\":false}}}],\"Custom-Built Workflows/UiDemo_Open.xaml\":[{\"ActivityIdRef\":\"GetSecureCredential_1\",\"IsAdvancedOptionsExpanded\":false,\"Widgets\":{}}],\"Custom-Built Workflows/UiDemo_Close.xaml\":[],\"Framework/GetTransactionData.xaml\":[{\"ActivityIdRef\":\"If_1\",\"IsAdvancedOptionsExpanded\":false,\"Widgets\":{}},{\"ActivityIdRef\":\"GetQueueItem_2\",\"IsAdvancedOptionsExpanded\":false,\"Categories\":{\"Options\":true,\"Output\":true},\"Widgets\":{}},{\"ActivityIdRef\":\"Rethrow_1\",\"IsAdvancedOptionsExpanded\":false,\"Widgets\":{}}],\"Custom-Built Workflows/UiDemo_ForceClose.xaml\":[{\"ActivityIdRef\":\"KillProcess_1\",\"IsAdvancedOptionsExpanded\":false,\"Widgets\":{}}]}","Compiler":"2","ProjectWatches":"{\"Value\":[]}"}